ebel_rest/__init__.py
ebel_rest/constants.py
ebel_rest/defaults.py
ebel_rest/manager/__init__.py
ebel_rest/manager/core.py
ebel_rest/manager/export.py
ebel_rest/manager/query.py
ebel_rest/manager/ss_functions.py
ebel_rest/manager/statistics.py
ebel_rest/visualisation/__init__.py
ebel_rest/visualisation/colours/__init__.py
ebel_rest/visualisation/colours/graphviz.py
ebel_rest-1.0.25.dist-info/METADATA
ebel_rest-1.0.25.dist-info/WHEEL
ebel_rest-1.0.25.dist-info/licenses/AUTHORS.rst
ebel_rest-1.0.25.dist-info/licenses/LICENSE
ebel_rest-1.0.25.dist-info/RECORD
