Metadata-Version: 2.1
Name: ebel_rest
Version: 1.0.25
Summary: e(BE:L) API client
Project-URL: repository, https://github.com/e-bel/ebel_rest
Author-email: Bruce Schultz <bruce.schultz@scai.fraunhofer.de>, Christian Ebeling <christian.ebeling@scai.fraunhofer.de>
Maintainer-email: Christian Ebeling <christian.ebeling@scai.fraunhofer.de>
License: MIT
License-File: AUTHORS.rst
License-File: LICENSE
Keywords: API,BEL,Knowledge Graph,OrientDB
Classifier: Development Status :: 4 - Beta
Classifier: Intended Audience :: Developers
Classifier: Intended Audience :: Science/Research
Classifier: Natural Language :: English
Classifier: Programming Language :: Python :: 3
Classifier: Programming Language :: Python :: 3.7
Classifier: Programming Language :: Python :: 3.8
Classifier: Programming Language :: Python :: 3.9
Classifier: Programming Language :: Python :: 3.10
Classifier: Programming Language :: Python :: 3.11
Classifier: Topic :: Scientific/Engineering :: Bio-Informatics
Requires-Python: >=3.7
Requires-Dist: graphviz
Requires-Dist: ipython
Requires-Dist: pandas
